link_ddui_to_airflow.py
ddui/__init__.py
ddui/dash_app.py
ddui/dash_components.py
ddui/orm.py
ddui/plot.py
ddui/plugin.py
ddui/views.py
ddui/static/brian/dd.css
ddui/static/brian/git.png
ddui/static/brian/sigle.png
ddui/templates/brian/dash.html
ddui-3.0.4.dist-info/LICENSE.txt
ddui-3.0.4.dist-info/METADATA
ddui-3.0.4.dist-info/WHEEL
ddui-3.0.4.dist-info/entry_points.txt
ddui-3.0.4.dist-info/top_level.txt
ddui-3.0.4.dist-info/RECORD
