Metadata-Version: 2.1
Name: ddui
Version: 3.0.4
Summary: UNKNOWN
Home-page: UNKNOWN
Author: UNKNOWN
Author-email: UNKNOWN
License: UNKNOWN
Platform: UNKNOWN
Requires-Dist: pandas
Requires-Dist: jinja2 (<2.9.0,>=2.7.3)
Requires-Dist: flask (<0.13,>=0.12.4)
Requires-Dist: apache-airflow (==1.10.*)
Requires-Dist: click
Requires-Dist: dash (==0.37.*)
Requires-Dist: dash-html-components (==0.13.*)
Requires-Dist: dash-core-components (==0.43.*)
Requires-Dist: dash-dagre (>=0.0.2)
Requires-Dist: dash-table (==3.4.*)
